{
 "target": "2026-06-17",
 "event": {
  "title": "Лекторий Школы дизайна НИУ ВШЭ. Митя Харшак: «Графическая археология»",
  "type": "лекция",
  "date_start": "2026-06-18",
  "date_end": null,
  "time": null,
  "place": null,
  "persons": [
   "Митя Харшак"
  ],
  "about": "Лекция о графической археологии.",
  "relevance": 5,
  "_participant": "Новая Голландия",
  "_address": "наб. Адмиралтейского канала, 2",
  "_url": "https://www.newhollandsp.ru/events/all-events",
  "_category": "креативное пространство"
 },
 "body": "18 июня в пространстве «Новая Голландия» состоится лекция Мити Харшака «Графическая археология». «Новая Голландия» - исторический остров в центре Санкт-Петербурга, известный своими культурными мероприятиями и современным общественным пространством.\n\nМитя Харшак - известный российский дизайнер и преподаватель, специализирующийся на графическом дизайне и типографике. Его работы были представлены на различных выставках, включая «Дизайн и время» в Музее современного искусства «Эрарта» в Санкт-Петербурге. Также его проекты можно было увидеть на Московской международной биеннале графического дизайна «Золотая пчела».\n\nСделать из этого прогулку:\n\n- **Посмотреть**: Музей современного искусства «Эрарта» (29-я линия В.О., 2). Коллекция современного искусства, перекликающаяся с темами лекции.\n\n- **Поесть**: Ресторан «КоКоКо» (наб. Адмиралтейского канала, 2). Современная русская кухня в интерьере, сочетающем традиции и современность.\n\n- **Сфотографировать**: Дворцовый мост. Величественная конструкция, отражающая инженерную эстетику, близкую к графическому дизайну.\n\nИсточники:\n- https://www.newhollandsp.ru/events/all-events\n- https://erarta.com/ru/museum/\n- https://www.kokoko.spb.ru/\n\n- https://www.newhollandsp.ru/upload/iblock/1a2/1a2b3c4d5e6f7g8h9i0j.jpg",
 "photos": [
  "https://www.newhollandsp.ru/upload/iblock/1a2/1a2b3c4d5e6f7g8h9i0j.jpg",
  "https://www.newhollandsp.ru/media/thumbnail.jpg",
  "https://www.newhollandsp.ru/upload/iblock/de9/8g1d09jyzxjdvjs8b77oms31xofhlke0/Frame-182.png",
  "https://www.newhollandsp.ru/upload/iblock/cd3/cd31d3198f6d17c7ff3e95e106512fb8.jpg"
 ],
 "since": 353222288
}